{
  "스키마명": "prod",                         
  "스키마 버전": "1",                         
  "토픽명": "prod",                              
  "관련 토픽": "user, prod",                   
  "관리부서": "운영 1팀",                            
  "업무 시스템": "gaia",                         
  "소스 시스템": "eshop",                             
  "싱크 시스템": "iris, mdw",                       
  "최종 수정자": "oyoy@goodusdata.com",       
  "생성일시": "2021-03-22 13:10:15",             
  "수정일시": "2021-03-23 14:10:20",             
  
  "meta": [
    {
        "물리명": "prod_id",                                                           
        "데이터 타입": "string",                                                        
        "논리명": "사용자번호",                                                        
        "필수여부" : "y",                                                            
        "기본값": "null",                                                             
        "설명": "상품 등록시 부여되는 유니크 값으로 순차적으로 증가한다",                          
        "민감정보 유무": "n",                                                              
        "연관토픽 연결필드": "null",                                                      
        "참고사항": "프로그램내에서 순차적으로 증가하는 값으로 의미를 내포하지 않음."                  
        },
    {
        "물리명": "prodname",                                                           
        "데이터 타입": "string",                                                        
        "논리명": "상품명",                                                        
        "필수여부" : "y",                                                            
        "기본값": "null",                                                             
        "설명": "상품명",                          
        "민감정보 유무": "n",                                                              
        "연관토픽 연결필드": "null",                                                      
        "참고사항": "동일 상품이라도 업체가 다르면 상품번호가 다름"                  
        },
    {
        "물리명": "provider",                                                           
        "데이터 타입": "string",                                                        
        "논리명": "업체명",                                                        
        "필수여부" : "y",                                                            
        "기본값": "null",                                                             
        "설명": "상품을 제공하는 업체 또는 등록된 셀러",                          
        "민감정보 유무": "n",                                                              
        "연관토픽 연결필드": "null",                                                      
        "참고사항": ""                  
        },
    {
        "물리명": "manufacturer",                                                           
        "데이터 타입": "string",                                                        
        "논리명": "제조사",                                                        
        "필수여부" : "y",                                                            
        "기본값": "null",                                                             
        "설명": "상품을 제조하는 제조 업체",                          
        "민감정보 유무": "n",                                                              
        "연관토픽 연결필드": "null",                                                      
        "참고사항": ""                  
        },
    {
        "물리명": "list_price",                                                           
        "데이터 타입": "string",                                                        
        "논리명": "상품 정가격",                                                        
        "필수여부" : "y",                                                            
        "기본값": "null",                                                             
        "설명": "할인되지 않은 상품 출시 가격",                          
        "민감정보 유무": "n",                                                              
        "연관토픽 연결필드": "null",                                                      
        "참고사항": ""                  
        }
      ]
}